fastmongo/__init__.py
fastmongo/basics.py
fastmongo/fast.py
fastmongo-0.0.47.dist-info/METADATA
fastmongo-0.0.47.dist-info/WHEEL
fastmongo-0.0.47.dist-info/RECORD
