Metadata-Version: 2.4
Name: fastmongo
Version: 0.0.47
Summary: make it easy to use pymongo
Project-URL: Homepage, https://gitee.com/ZeroSeeker/fastmongo
Project-URL: Issues, https://gitee.com/ZeroSeeker/fastmongo/issues
Author-email: ZeroSeeker <zeroseeker@foxmail.com>
License-Expression: MIT
Classifier: Operating System :: OS Independent
Classifier: Programming Language :: Python :: 3
Requires-Python: >=3.8
Requires-Dist: envx>=1.0.1
Requires-Dist: pymongo==4.10.1
Requires-Dist: showlog>=0.0.6
